mohawk/__init__.py
mohawk/base.py
mohawk/bewit.py
mohawk/exc.py
mohawk/receiver.py
mohawk/sender.py
mohawk/tests.py
mohawk/util.py
mohawk-1.0.0.dist-info/DESCRIPTION.rst
mohawk-1.0.0.dist-info/METADATA
mohawk-1.0.0.dist-info/RECORD
mohawk-1.0.0.dist-info/WHEEL
mohawk-1.0.0.dist-info/metadata.json
mohawk-1.0.0.dist-info/top_level.txt
