Metadata-Version: 1.1
Name: mohawk
Version: 1.0.0
Summary: Library for Hawk HTTP authorization
Home-page: https://github.com/kumar303/mohawk
Author: Kumar McMillan, Austin King
Author-email: kumar.mcmillan@gmail.com
License: MPL 2.0 (Mozilla Public License)
Platform: UNKNOWN
Classifier: Intended Audience :: Developers
Classifier: Natural Language :: English
Classifier: Operating System :: OS Independent
Classifier: Programming Language :: Python :: 2
Classifier: Programming Language :: Python :: 3
Classifier: Programming Language :: Python :: 2.6
Classifier: Programming Language :: Python :: 2.7
Classifier: Programming Language :: Python :: 3.4
Classifier: Programming Language :: Python :: 3.5
Classifier: Programming Language :: Python :: 3.6
Classifier: Programming Language :: Python :: 3.7
Classifier: Topic :: Internet :: WWW/HTTP
